pageextractor/__init__.py
pageextractor-0.1.8.dist-info/licenses/LICENSE
pageextractor-0.1.8.dist-info/WHEEL
pageextractor-0.1.8.dist-info/METADATA
pageextractor-0.1.8.dist-info/RECORD
