Metadata-Version: 2.4
Name: pageextractor
Version: 0.1.8
Summary: Use SAM2 to extract and warp a page from a photo.
Author: Herbert Kruitbosch
Author-email: Herbert Kruitbosch <H.T.Kruitbosch@rug.nl>
License-Expression: Apache-2.0
License-File: LICENSE
Requires-Dist: gradio>=5.29.0
Requires-Dist: litserve>=0.2.8
Requires-Dist: opencv-python-headless>=4.10.0.84
Requires-Dist: pillow>=10.2.0
Requires-Dist: rasterio>=1.4.3
Requires-Dist: sam2
Requires-Dist: scikit-image>=0.24.0
Requires-Dist: shapely>=2.1.1
Requires-Dist: supervision>=0.23.0
Requires-Dist: torch>=2.3.1
Requires-Dist: torchvision>=0.18.1
Requires-Dist: tqdm>=4.67.1
Requires-Dist: transformers>=4.44.2
Requires-Python: >=3.10
Project-URL: Homepage, https://github.com/UG-Team-Data-Science/pageextractor
Project-URL: Issues, https://github.com/UG-Team-Data-Science/pageextractor/issues
